rh_xml_tong/__init__.py
rh_xml_tong/cli.py
rh_xml_tong/config.py
rh_xml_tong/core.py
rh_xml_tong/utils.py
rh_xml_tong/validator.py
rh_xml_tong-0.1.7.dist-info/licenses/LICENSE
rh_xml_tong-0.1.7.dist-info/METADATA
rh_xml_tong-0.1.7.dist-info/WHEEL
rh_xml_tong-0.1.7.dist-info/entry_points.txt
rh_xml_tong-0.1.7.dist-info/top_level.txt
rh_xml_tong-0.1.7.dist-info/RECORD
