Metadata-Version: 2.4
Name: rh-xml-tong
Version: 0.1.7
Summary: 专业的中国人民银行XML征信数据处理工具库，支持批量处理、智能验证、错误检测，工作日常用到，因此封装为库！
Home-page: https://tongblog-61e.pages.dev/
Author: Tong
Author-email: Tong <litong0923@gmail.com>
License: MIT License
Project-URL: Homepage, https://tongblog-61e.pages.dev/
Project-URL: Documentation, https://github.com/yourusername/rh-xml-tong/wiki
Project-URL: Repository, https://github.com/yourusername/rh-xml-tong
Project-URL: Bug Tracker, https://github.com/yourusername/rh-xml-tong/issues
Classifier: Development Status :: 3 - Alpha
Classifier: Intended Audience :: Financial and Insurance Industry
Classifier: Intended Audience :: Developers
Classifier: Topic :: Office/Business :: Financial
Classifier: License :: OSI Approved :: MIT License
Classifier: Programming Language :: Python :: 3
Classifier: Programming Language :: Python :: 3.7
Classifier: Programming Language :: Python :: 3.8
Classifier: Programming Language :: Python :: 3.9
Classifier: Programming Language :: Python :: 3.10
Classifier: Programming Language :: Python :: 3.11
Requires-Python: >=3.7
License-File: LICENSE
Requires-Dist: pandas>=1.0.0
Requires-Dist: numpy>=1.18.0
Requires-Dist: tqdm>=4.50.0
Dynamic: author
Dynamic: home-page
Dynamic: license-file
Dynamic: requires-python
